laftel/__init__.py
laftel/laftel.py
laftel/models.py
laftel/utils.py
laftel-1.3.1.dist-info/LICENSE
laftel-1.3.1.dist-info/METADATA
laftel-1.3.1.dist-info/WHEEL
laftel-1.3.1.dist-info/top_level.txt
laftel-1.3.1.dist-info/RECORD
