Metadata-Version: 2.1
Name: laftel
Version: 1.3.1
Summary: 파이썬 라프텔 라이브러리, Unofficial Python Laftel API Wrapper(Laftel)
Home-page: https://github.com/331leo/laftel
Download-URL: https://github.com/331leo/laftel
Author: LeoK
Author-email: support@leok.kr
License: GPL-V3
Keywords: anime,laftel,info,API,wrapper
Classifier: Programming Language :: Python :: 3.9
Classifier: Programming Language :: Python :: 3.8
Classifier: Programming Language :: Python :: 3.7
Classifier: Programming Language :: Python :: 3.6
Classifier: License :: OSI Approved :: GNU General Public License v3 (GPLv3)
Classifier: Development Status :: 3 - Alpha
Requires-Python: >=3.6
License-File: LICENSE
Requires-Dist: aiohttp
